dolphin/__init__.py
dolphin/ai/__init__.py
dolphin/ai/ai.py
dolphin/ai/modeler.py
dolphin/ai/vision.py
dolphin/analysis/__init__.py
dolphin/analysis/output.py
dolphin/processor/__init__.py
dolphin/processor/config.py
dolphin/processor/core.py
dolphin/processor/data.py
dolphin/processor/files.py
dolphin/processor/recipe.py
space_dolphin-1.2.0.dist-info/licenses/AUTHORS.rst
space_dolphin-1.2.0.dist-info/licenses/LICENSE
space_dolphin-1.2.0.dist-info/METADATA
space_dolphin-1.2.0.dist-info/WHEEL
space_dolphin-1.2.0.dist-info/top_level.txt
space_dolphin-1.2.0.dist-info/RECORD
