Metadata-Version: 2.4
Name: space-dolphin
Version: 1.2.0
Summary: Automated pipeline for lens modeling based on lenstronomy
Home-page: https://github.com/ajshajib/dolphin
Author: Anowar J. Shajib
Author-email: "Anowar J. Shajib" <ajshajib@gmail.com>
License-Expression: BSD-3-Clause
Project-URL: Homepage, https://github.com/ajshajib/dolphin
Keywords: dolphin,lenstronomy
Classifier: Development Status :: 5 - Production/Stable
Classifier: Intended Audience :: Science/Research
Classifier: Natural Language :: English
Classifier: Programming Language :: Python :: 3.9
Classifier: Programming Language :: Python :: 3.10
Classifier: Programming Language :: Python :: 3.11
Classifier: Programming Language :: Python :: 3.12
Requires-Python: >=3.9
License-File: LICENSE
License-File: AUTHORS.rst
Dynamic: author
Dynamic: home-page
Dynamic: license-file
Dynamic: requires-python
